flex/stream/__init__.py
flex/stream/_version.py
flex/stream/batch_handler.py
flex/stream/py.typed
flex/stream/task_logging.py
flex_streaming_sdk-0.1.0.dist-info/WHEEL
flex_streaming_sdk-0.1.0.dist-info/METADATA
flex_streaming_sdk-0.1.0.dist-info/RECORD
