Metadata-Version: 2.4
Name: flex-streaming-sdk
Version: 0.1.0
Summary: Handy tools for streaming data
Requires-Python: >= 3.9
Requires-Dist: azure-eventhub>=5
Requires-Dist: azure-identity>=1
